LICENSE
README.md
setup.py
CoolBar/CoolBar.py
CoolBar/__init__.py
CoolBar/animations.py
CoolBar.egg-info/PKG-INFO
CoolBar.egg-info/SOURCES.txt
CoolBar.egg-info/dependency_links.txt
CoolBar.egg-info/top_level.txt